galaxybox/.gitignore
galaxybox/__init__.py
galaxybox/configs/__init__.py
galaxybox/configs/emerge-galaxy.alias.yaml
galaxybox/data/__init__.py
galaxybox/data/cosmic_time.py
galaxybox/data/utils.py
galaxybox/modules/__init__.py
galaxybox/modules/mocks/__init__.py
galaxybox/modules/mocks/lightcone.py
galaxybox/modules/trees/emerge.py
galaxybox/modules/trees/proto_tree.py
galaxybox/utils/__init__.py
galaxybox/utils/functions.py
galaxybox/utils/logmath.py
galaxybox/visualization/__init__.py
galaxybox/visualization/emerge_plot.py
galaxybox/visualization/plot.py
galaxybox/visualization/tree.py
galaxybox-2.0.3.dist-info/METADATA
galaxybox-2.0.3.dist-info/WHEEL
galaxybox-2.0.3.dist-info/licenses/LICENSE
galaxybox-2.0.3.dist-info/RECORD
