Metadata-Version: 2.4
Name: galaxybox
Version: 2.0.3
Summary: Add your description here
Author-email: Joseph O'Leary <oleary.joseph@outlook.com>
License-File: LICENSE
Requires-Python: >=3.11
Requires-Dist: astropy>=7.1.0
Requires-Dist: h5py>=3.14.0
Requires-Dist: halotools>=0.9.3
Requires-Dist: matplotlib>=3.10.3
Requires-Dist: numpy>=2.3.0
Requires-Dist: pandas[parquet]>=2.3.0
Requires-Dist: pyyaml>=6.0.2
Requires-Dist: scipy>=1.15.3
Requires-Dist: seaborn>=0.13.2
Requires-Dist: shapely>=2.1.1
Requires-Dist: tables>=3.10.2
Requires-Dist: tqdm>=4.67.1
